odoo/addons/l10n_ir_account/README.rst
odoo/addons/l10n_ir_account/__init__.py
odoo/addons/l10n_ir_account/__manifest__.py
odoo/addons/l10n_ir_account/data/res.bank.csv
odoo/addons/l10n_ir_account/data/res_currency_data.xml
odoo/addons/l10n_ir_account/data/template/account.account-ir.csv
odoo/addons/l10n_ir_account/data/template/account.fiscal.position-ir.csv
odoo/addons/l10n_ir_account/data/template/account.group-ir.csv
odoo/addons/l10n_ir_account/data/template/account.tax-ir.csv
odoo/addons/l10n_ir_account/data/template/account.tax.group-ir.csv
odoo/addons/l10n_ir_account/i18n/l10n_ir_account.pot
odoo/addons/l10n_ir_account/models/__init__.py
odoo/addons/l10n_ir_account/models/template_ir.py
odoo/addons/l10n_ir_account/static/description/icon.png
odoo_addon_l10n_ir_account-18.0.1.0.0.3.dist-info/METADATA
odoo_addon_l10n_ir_account-18.0.1.0.0.3.dist-info/WHEEL
odoo_addon_l10n_ir_account-18.0.1.0.0.3.dist-info/top_level.txt
odoo_addon_l10n_ir_account-18.0.1.0.0.3.dist-info/RECORD
